Metadata-Version: 1.0
Name: hellomars
Version: 1.0.0
Summary: Say hello to Mars.
Home-page: https://github.com/ryanyuan/hellomars
Author: Ryan Yuan
Author-email: ryan.yuan@outlook.com
License: UNKNOWN
Platform: UNKNOWN
